simuvex/__init__.py
simuvex/s_action.py
simuvex/s_action_object.py
simuvex/s_cc.py
simuvex/s_errors.py
simuvex/s_event.py
simuvex/s_format.py
simuvex/s_options.py
simuvex/s_pcap.py
simuvex/s_procedure.py
simuvex/s_slicer.py
simuvex/s_state.py
simuvex/s_type.py
simuvex/s_type_backend.py
simuvex/s_variable.py
simuvex/concretization_strategies/__init__.py
simuvex/concretization_strategies/any.py
simuvex/concretization_strategies/max.py
simuvex/concretization_strategies/nonzero.py
simuvex/concretization_strategies/nonzero_range.py
simuvex/concretization_strategies/norepeats.py
simuvex/concretization_strategies/norepeats_range.py
simuvex/concretization_strategies/range.py
simuvex/concretization_strategies/single.py
simuvex/concretization_strategies/solutions.py
simuvex/engines/__init__.py
simuvex/engines/engine.py
simuvex/engines/procedure.py
simuvex/engines/successors.py
simuvex/engines/unicorn_engine.py
simuvex/engines/vex/__init__.py
simuvex/engines/vex/ccall.py
simuvex/engines/vex/dirty.py
simuvex/engines/vex/engine.py
simuvex/engines/vex/irop.py
simuvex/engines/vex/expressions/__init__.py
simuvex/engines/vex/expressions/base.py
simuvex/engines/vex/expressions/bbptr.py
simuvex/engines/vex/expressions/ccall.py
simuvex/engines/vex/expressions/const.py
simuvex/engines/vex/expressions/get.py
simuvex/engines/vex/expressions/geti.py
simuvex/engines/vex/expressions/ite.py
simuvex/engines/vex/expressions/load.py
simuvex/engines/vex/expressions/op.py
simuvex/engines/vex/expressions/rdtmp.py
simuvex/engines/vex/expressions/unsupported.py
simuvex/engines/vex/expressions/vecret.py
simuvex/engines/vex/statements/__init__.py
simuvex/engines/vex/statements/abihint.py
simuvex/engines/vex/statements/base.py
simuvex/engines/vex/statements/cas.py
simuvex/engines/vex/statements/dirty.py
simuvex/engines/vex/statements/exit.py
simuvex/engines/vex/statements/imark.py
simuvex/engines/vex/statements/llsc.py
simuvex-6.7.1.31.dist-info/DESCRIPTION.rst
simuvex-6.7.1.31.dist-info/METADATA
simuvex-6.7.1.31.dist-info/RECORD
simuvex-6.7.1.31.dist-info/WHEEL
simuvex-6.7.1.31.dist-info/metadata.json
simuvex-6.7.1.31.dist-info/top_level.txt
