Metadata-Version: 2.0
Name: simuvex
Version: 6.7.1.31
Summary: A symbolic execution engine for the VEX IR
Home-page: https://github.com/angr/simuvex
Author: UNKNOWN
Author-email: UNKNOWN
License: UNKNOWN
Platform: UNKNOWN
Requires-Dist: ana
Requires-Dist: archinfo
Requires-Dist: bintrees
Requires-Dist: cachetools
Requires-Dist: claripy
Requires-Dist: cooldict
Requires-Dist: dpkt-fix
Requires-Dist: enum34
Requires-Dist: pyvex
Requires-Dist: unicorn
